foragax/__init__.py
foragax/base/__init__.py
foragax/base/agent_classes.py
foragax/base/agent_methods.py
foragax/base/space_classes.py
foragax/base/space_methods.py
foragax/policy/__init__.py
foragax/policy/random_policy.py
foragax/policy/wilson_cowan.py
foragax-0.0.5.dist-info/METADATA
foragax-0.0.5.dist-info/WHEEL
foragax-0.0.5.dist-info/licenses/LICENSE.md
foragax-0.0.5.dist-info/RECORD
