Metadata-Version: 2.3
Name: foragax
Version: 0.0.5
Summary: ABM package in JAX.
Author-email: Siddharth Chaturvedi <sidchat.sc@gmail.com>
License:                                  Apache License
License-File: LICENSE.md
Keywords: ABM,Agent-Based-Modeling,abm,agent-based-modeling,foragax,foraging,jax,simulation
Classifier: Development Status :: 3 - Alpha
Classifier: Intended Audience :: Developers
Classifier: License :: OSI Approved :: Apache Software License
Classifier: Natural Language :: English
Classifier: Programming Language :: Python :: 3
Classifier: Topic :: Scientific/Engineering :: Artificial Intelligence
Requires-Python: ~=3.10
Requires-Dist: flax>=0.7.4
Requires-Dist: jax>=0.4.13
